{"inkVersion":20,"root":[[["^Hey look, theres a box next to me!","\n","ev","str","^Inspect the box","/str","/ev",{"*":".^.c-0","flg":20},{"c-0":["\n",{"->":"0.g-1"},{"#f":5}],"#f":5,"#n":"g-0"}],{"g-1":["^This isn't just any box. That's the  Junior Parapsychologist's Weekly Gift Box that my parents got for me! You read the slogan on the side: \"The Essential tools that any ghost reseacher needs!\" Maybe one day you'll be a ghost reseacher.","\n","ev","str","^Open the Junior Parapsychologist's Weekly Gift Box","/str","/ev",{"*":".^.c-1","flg":20},{"c-1":["\n",{"->":"0.g-2"},{"#f":5}],"#f":5}],"g-2":["^You rip open the paper wrapping and find a round case inside. The case reads: Parapsychological Ghost Glasses ",{"#":"delete ghostbox"},"\n","ev","str","^Put on Ghost Glasses","/str","/ev",{"*":".^.c-2","flg":20},{"c-2":["\n",{"->":"0.g-3"},{"#f":5}],"#f":5}],"g-3":["^You put on the glasses and look around. ",{"#":"gain glasses"},"\n",["done",{"#f":5,"#n":"g-4"}],{"#f":5}]}],"done",{"global decl":["ev","str","^BLUE BOX","/str",{"VAR=":"title"},"/ev","end",null],"#f":1}],"listDefs":{}}